{
  "indexes": [
    {
      "collectionGroup": "progress",
      "queryScope": "COLLECTION",
      "fields": [
        {
          "fieldPath": "uid",
          "order": "ASCENDING"
        },
        {
          "fieldPath": "courseId",
          "order": "ASCENDING"
        },
        {
          "fieldPath": "lastUpdated",
          "order": "DESCENDING"
        }
      ]
    },
    {
      "collectionGroup": "quiz_results",
      "queryScope": "COLLECTION",
      "fields": [
        {
          "fieldPath": "uid",
          "order": "ASCENDING"
        },
        {
          "fieldPath": "completedAt",
          "order": "DESCENDING"
        }
      ]
    },
    {
      "collectionGroup": "quiz_results",
      "queryScope": "COLLECTION",
      "fields": [
        {
          "fieldPath": "uid",
          "order": "ASCENDING"
        },
        {
          "fieldPath": "lessonId",
          "order": "ASCENDING"
        },
        {
          "fieldPath": "completedAt",
          "order": "DESCENDING"
        }
      ]
    },
    {
      "collectionGroup": "users",
      "queryScope": "COLLECTION",
      "fields": [
        {
          "fieldPath": "plan",
          "order": "ASCENDING"
        },
        {
          "fieldPath": "lastActive",
          "order": "DESCENDING"
        }
      ]
    },
    {
      "collectionGroup": "users",
      "queryScope": "COLLECTION",
      "fields": [
        {
          "fieldPath": "streak",
          "order": "DESCENDING"
        },
        {
          "fieldPath": "xp",
          "order": "DESCENDING"
        }
      ]
    },
    {
      "collectionGroup": "users",
      "queryScope": "COLLECTION",
      "fields": [
        {
          "fieldPath": "streak",
          "order": "ASCENDING"
        },
        {
          "fieldPath": "lastStudiedDate",
          "order": "ASCENDING"
        }
      ]
    },
    {
      "collectionGroup": "subscriptions",
      "queryScope": "COLLECTION",
      "fields": [
        {
          "fieldPath": "uid",
          "order": "ASCENDING"
        },
        {
          "fieldPath": "status",
          "order": "ASCENDING"
        },
        {
          "fieldPath": "expiresAt",
          "order": "DESCENDING"
        }
      ]
    },
    {
      "collectionGroup": "notifications",
      "queryScope": "COLLECTION_GROUP",
      "fields": [
        {
          "fieldPath": "read",
          "order": "ASCENDING"
        },
        {
          "fieldPath": "createdAt",
          "order": "DESCENDING"
        }
      ]
    },
    {
      "collectionGroup": "chat_history",
      "queryScope": "COLLECTION_GROUP",
      "fields": [
        {
          "fieldPath": "createdAt",
          "order": "DESCENDING"
        }
      ]
    },
    {
      "collectionGroup": "lessons",
      "queryScope": "COLLECTION",
      "fields": [
        {
          "fieldPath": "moduleId",
          "order": "ASCENDING"
        },
        {
          "fieldPath": "order",
          "order": "ASCENDING"
        }
      ]
    },
    {
      "collectionGroup": "lessons",
      "queryScope": "COLLECTION",
      "fields": [
        {
          "fieldPath": "courseId",
          "order": "ASCENDING"
        },
        {
          "fieldPath": "moduleId",
          "order": "ASCENDING"
        },
        {
          "fieldPath": "order",
          "order": "ASCENDING"
        }
      ]
    },
    {
      "collectionGroup": "lessons",
      "queryScope": "COLLECTION",
      "fields": [
        {
          "fieldPath": "courseId",
          "order": "ASCENDING"
        },
        {
          "fieldPath": "xpReward",
          "order": "DESCENDING"
        }
      ]
    }
  ],
  "fieldOverrides": []
}